pybticino/__init__.py
pybticino/account.py
pybticino/auth.py
pybticino/const.py
pybticino/exceptions.py
pybticino/home.py
pybticino/models.py
pybticino/module.py
pybticino/websocket.py
pybticino-1.3.dist-info/licenses/LICENSE.txt
pybticino-1.3.dist-info/METADATA
pybticino-1.3.dist-info/WHEEL
pybticino-1.3.dist-info/top_level.txt
pybticino-1.3.dist-info/RECORD
