Metadata-Version: 2.4
Name: pybticino
Version: 1.3
Summary: Simple API to access BTicino/Legrand Classe 100X/300X devices
Author-email: k-the-hidden-hero <git@k8s.one>
Maintainer-email: k-the-hidden-hero <git@k8s.one>
Project-URL: Homepage, https://github.com/k-the-hidden-hero/pybticino
Project-URL: Repository, https://github.com/k-the-hidden-hero/pybticino.git
Project-URL: Issues, https://github.com/k-the-hidden-hero/pybticino/issues
Project-URL: Changelog, https://github.com/k-the-hidden-hero/pybticino/blob/main/CHANGELOG.md
Classifier: Development Status :: 4 - Beta
Classifier: Intended Audience :: Developers
Classifier: Topic :: Home Automation
Classifier: License :: OSI Approved :: MIT License
Classifier: Programming Language :: Python :: 3
Classifier: Programming Language :: Python :: 3 :: Only
Classifier: Programming Language :: Python :: 3.11
Classifier: Programming Language :: Python :: 3.12
Classifier: Programming Language :: Python :: Implementation :: CPython
Classifier: Programming Language :: Python :: Implementation :: PyPy
Requires-Python: <3.14,>=3.11
License-File: LICENSE.txt
Requires-Dist: websockets>=14.0
Requires-Dist: aiohttp>=3.11.16
Dynamic: license-file
